README.md
setup.cfg
setup.py
gasyncio/__init__.py
gasyncio/gevents.py
gasyncio.egg-info/PKG-INFO
gasyncio.egg-info/SOURCES.txt
gasyncio.egg-info/dependency_links.txt
gasyncio.egg-info/top_level.txt