Metadata-Version: 2.1
Name: gasyncio
Version: 0.0.1
Summary: A minimalistic asyncio event loop based on the GLib main event loop
Home-page: https://github.com/begnac/gasyncio
Author: Itaï BEN YAACOV
Author-email: candeb@free.fr
License: LGPLv2.1+
Keywords: asyncio,GLib
Platform: UNKNOWN
Classifier: Development Status :: 3 - Alpha
Classifier: Intended Audience :: Developers
Classifier: License :: OSI Approved :: GNU Library or Lesser General Public License (LGPL)
Classifier: Operating System :: POSIX :: Linux
Classifier: Programming Language :: Python :: 3
Classifier: Programming Language :: Python :: 3.9
